api_to_pydantic_utils/README.md
api_to_pydantic_utils/__init__.py
api_to_pydantic_utils/json_checker.py
api_to_pydantic_utils/model_tester.py
api_to_pydantic_utils/schema_extractor.py
api_to_pydantic_utils-0.1.1.dist-info/licenses/LICENSE
api_to_pydantic_utils-0.1.1.dist-info/METADATA
api_to_pydantic_utils-0.1.1.dist-info/WHEEL
api_to_pydantic_utils-0.1.1.dist-info/top_level.txt
api_to_pydantic_utils-0.1.1.dist-info/RECORD
