Metadata-Version: 2.4
Name: api-to-pydantic-utils
Version: 0.1.1
Summary: Utilities for JSON schema extraction and Pydantic model generation
Author-email: Lucas Pimentel <lucas_cpimentel@proton.me>
Maintainer-email: Lucas Pimentel <lucas_cpimentel@proton.me>
License: MIT
Project-URL: Homepage, https://github.com/luc-pimentel/api-to-pydantic
Project-URL: Repository, https://github.com/luc-pimentel/api-to-pydantic
Project-URL: Documentation, https://github.com/luc-pimentel/api-to-pydantic#readme
Project-URL: Bug Tracker, https://github.com/luc-pimentel/api-to-pydantic/issues
Keywords: pydantic,json,schema,api,validation,type-hints
Classifier: Development Status :: 4 - Beta
Classifier: Intended Audience :: Developers
Classifier: License :: OSI Approved :: MIT License
Classifier: Operating System :: OS Independent
Classifier: Programming Language :: Python :: 3
Classifier: Programming Language :: Python :: 3.8
Classifier: Programming Language :: Python :: 3.9
Classifier: Programming Language :: Python :: 3.10
Classifier: Programming Language :: Python :: 3.11
Classifier: Programming Language :: Python :: 3.12
Classifier: Topic :: Software Development :: Libraries :: Python Modules
Classifier: Topic :: Internet :: WWW/HTTP :: Dynamic Content
Classifier: Topic :: Software Development :: Code Generators
Requires-Python: >=3.8
License-File: LICENSE
Provides-Extra: dev
Requires-Dist: pytest>=7.0.0; extra == "dev"
Requires-Dist: pytest-cov>=4.0.0; extra == "dev"
Requires-Dist: black>=23.0.0; extra == "dev"
Requires-Dist: isort>=5.12.0; extra == "dev"
Requires-Dist: mypy>=1.0.0; extra == "dev"
Dynamic: license-file
